{
	"name": "uploadcustomwidget",
	"description": "Custom widget to upload documents",
	"newInstancePrefix": "uploadwidget",
	"eula": "",
	"vendor": "Simon",
	"license": "",
	"id": "tyfuploadbtn",
	"version": "1.0.0",
	"icon": "https://cdn.pixabay.com/photo/2016/01/03/00/43/upload-1118929_960_720.png",
	"webcomponents": [
		{
			"kind": "main",
			"tag": "upload-feature",
			"url": "https://stephansadou.github.io/ssrepo.github.io/customwidget/uploadfeature/uploaddocument.js",
			"integrity": ""	,
			"ignoreIntegrity": true
			
		}		
	],
	"properties": {
		"width": {
			"type": "integer",
			"default": 400
		},
		"height": {
			"type": "integer",
			"default": 275
		}
	},
	"methods": {
		"clear": {
			"description": "Clear the resultset"
		}
	},
	"events": {
		"onStart": {
      			"description": "Specify the SAC Script that shall be triggered when the Export process is started."
		},
		"onClick": {
			"description": "Called when the user clicks the button."
		}, 
		"onSubmit": {
			"description": "Submit when all information in form is submitted."
		},
		"onChange": {
			"description": "Event triggered if there are any changes."
		}
	}
}
